{"hex_id": "8860145947fffff", "cis_score": 42.7, "cis_category": "moderate", "total_violations": 103, "daily_average": 4.9, "carriageway_reduction": 14.5, "lat": 13.034604, "lng": 77.557355, "location_name": "MS Ramaiah Road, Nada Prabhu Kempegowda Circle, Mathikere, Bengaluru, Karnataka. Pin-560054 (India)", "police_station": "Yeshwanthpura", "junction_name": "No Junction", "is_junction": false, "dominant_violation": "WRONG PARKING", "dominant_vehicle": "CAR", "peak_hour": 3, "temporal_matrix": [[0.0, 0.0, 0.0, 0.0, 9.0, 0.0, 0.0, 0.0, 0.0, 0.0, 0.0, 0.0, 0.0, 0.0, 0.0, 0.0, 0.0, 0.0, 0.0, 0.0, 0.0, 0.0, 0.0, 0.0], [0.0, 0.0, 0.0, 0.0, 0.0, 1.0, 0.0, 0.0, 0.0, 0.0, 2.0, 0.0, 0.0, 0.0, 0.0, 0.0, 0.0, 0.0, 0.0, 0.0, 0.0, 0.0, 0.0, 0.0], [2.0, 0.0, 4.0, 20.0, 0.0, 0.0, 0.0, 0.0, 0.0, 0.0, 0.0, 0.0, 0.0, 0.0, 0.0, 0.0, 0.0, 0.0, 0.0, 0.0, 0.0, 0.0, 0.0, 0.0], [0.0, 0.0, 0.0, 10.0, 0.0, 5.0, 0.0, 0.0, 0.0, 0.0, 0.0, 0.0, 0.0, 1.0, 0.0, 0.0, 0.0, 0.0, 0.0, 0.0, 0.0, 0.0, 0.0, 0.0], [1.0, 0.0, 5.0, 16.0, 6.0, 0.0, 0.0, 0.0, 0.0, 0.0, 0.0, 0.0, 1.0, 0.0, 0.0, 0.0, 0.0, 0.0, 0.0, 0.0, 0.0, 0.0, 0.0, 0.0], [0.0, 0.0, 0.0, 1.0, 0.0, 1.0, 0.0, 0.0, 1.0, 0.0, 0.0, 14.0, 0.0, 0.0, 0.0, 0.0, 0.0, 0.0, 0.0, 0.0, 0.0, 0.0, 0.0, 0.0], [0.0, 0.0, 1.0, 0.0, 0.0, 0.0, 0.0, 0.0, 0.0, 0.0, 2.0, 0.0, 0.0, 0.0, 0.0, 0.0, 0.0, 0.0, 0.0, 0.0, 0.0, 0.0, 0.0, 0.0]], "violation_breakdown": {"WRONG PARKING": 84, "NO PARKING": 21, "PARKING IN A MAIN ROAD": 18, "DEFECTIVE NUMBER PLATE": 7, "PARKING ON FOOTPATH": 4}, "vehicle_breakdown": {"CAR": 47, "SCOOTER": 27, "MOTOR CYCLE": 10, "PASSENGER AUTO": 7, "MOPED": 4, "LGV": 2, "HGV": 2, "VAN": 1, "GOODS AUTO": 1, "OTHERS": 1}, "monthly_trend": {"2023-11": 63, "2023-12": 20, "2024-01": 16, "2024-02": 2, "2024-03": 2}, "hourly_distribution": {"0": 3, "2": 10, "3": 47, "4": 15, "5": 7, "8": 1, "10": 4, "11": 14, "12": 1, "13": 1}, "neighbors": [{"hex_id": "8860145941fffff", "cis_score": 43.3, "violations": 82}, {"hex_id": "8860145945fffff", "cis_score": 41.2, "violations": 20}, {"hex_id": "886014590dfffff", "cis_score": 44.7, "violations": 20}, {"hex_id": "8860145909fffff", "cis_score": 17.2, "violations": 1}, {"hex_id": "8860145943fffff", "cis_score": 42.6, "violations": 12}], "ai_insight": "This hotspot in Yeshwanthpura averages 5 violations/day, peaking at 03:00. Primarily WRONG PARKING by CARs (47 incidents). on an arterial road, causing an estimated 15% carriageway reduction. CIS score: 42.7/100 (moderate)."}