{"hex_id": "88618925e9fffff", "cis_score": 28.4, "cis_category": "low", "total_violations": 55, "daily_average": 1.6, "carriageway_reduction": 4.3, "lat": 12.938034, "lng": 77.62682, "location_name": "Srinivagilu Main Road, Sony World Junction, Koramangala, Bengaluru, Karnataka. Pin-560034 (India)", "police_station": "Adugodi", "junction_name": "No Junction", "is_junction": false, "dominant_violation": "WRONG PARKING", "dominant_vehicle": "SCOOTER", "peak_hour": 13, "temporal_matrix": [[0.0, 0.0, 0.0, 0.0, 1.0, 1.0, 0.0, 0.0, 0.0, 0.0, 0.0, 1.0, 0.0, 2.0, 0.0, 0.0, 0.0, 0.0, 0.0, 0.0, 0.0, 0.0, 0.0, 0.0], [0.0, 0.0, 0.0, 0.0, 0.0, 1.0, 0.0, 0.0, 0.0, 0.0, 0.0, 2.0, 1.0, 1.0, 0.0, 0.0, 0.0, 0.0, 0.0, 0.0, 0.0, 0.0, 0.0, 0.0], [0.0, 0.0, 0.0, 0.0, 1.0, 1.0, 0.0, 0.0, 0.0, 0.0, 0.0, 2.0, 0.0, 0.0, 3.0, 0.0, 0.0, 0.0, 0.0, 0.0, 0.0, 0.0, 0.0, 0.0], [0.0, 0.0, 4.0, 0.0, 2.0, 3.0, 1.0, 0.0, 0.0, 0.0, 0.0, 0.0, 1.0, 1.0, 0.0, 0.0, 0.0, 0.0, 0.0, 0.0, 0.0, 0.0, 0.0, 0.0], [0.0, 0.0, 0.0, 0.0, 2.0, 1.0, 0.0, 0.0, 0.0, 0.0, 0.0, 0.0, 1.0, 2.0, 1.0, 0.0, 0.0, 0.0, 0.0, 0.0, 0.0, 0.0, 0.0, 0.0], [1.0, 0.0, 0.0, 0.0, 1.0, 0.0, 1.0, 0.0, 0.0, 0.0, 0.0, 1.0, 2.0, 1.0, 1.0, 0.0, 0.0, 0.0, 0.0, 0.0, 0.0, 0.0, 0.0, 0.0], [0.0, 0.0, 0.0, 0.0, 0.0, 0.0, 2.0, 0.0, 0.0, 0.0, 0.0, 0.0, 1.0, 4.0, 4.0, 0.0, 0.0, 0.0, 0.0, 0.0, 0.0, 0.0, 0.0, 0.0]], "violation_breakdown": {"WRONG PARKING": 39, "NO PARKING": 16, "DEFECTIVE NUMBER PLATE": 2, "PARKING ON FOOTPATH": 1}, "vehicle_breakdown": {"SCOOTER": 28, "MOTOR CYCLE": 19, "CAR": 4, "VAN": 1, "MOPED": 1, "MAXI-CAB": 1, "LGV": 1}, "monthly_trend": {"2023-11": 6, "2023-12": 30, "2024-01": 17, "2024-02": 1, "2024-03": 1}, "hourly_distribution": {"0": 1, "2": 4, "4": 7, "5": 7, "6": 4, "11": 6, "12": 6, "13": 11, "14": 9}, "neighbors": [{"hex_id": "8861892513fffff", "cis_score": 31.7, "violations": 116}, {"hex_id": "8861892517fffff", "cis_score": 17.0, "violations": 3}, {"hex_id": "88618925edfffff", "cis_score": 15.6, "violations": 7}, {"hex_id": "88618925e1fffff", "cis_score": 45.1, "violations": 9}, {"hex_id": "88618925ebfffff", "cis_score": 45.8, "violations": 88}, {"hex_id": "88618925c5fffff", "cis_score": 27.3, "violations": 32}], "ai_insight": "This hotspot in Adugodi averages 2 violations/day, peaking at 13:00. Primarily WRONG PARKING by SCOOTERs (28 incidents). causing an estimated 4% carriageway reduction. CIS score: 28.4/100 (low)."}