{"hex_id": "8861892eb7fffff", "cis_score": 17.2, "cis_category": "low", "total_violations": 2, "daily_average": 2.0, "carriageway_reduction": 6.0, "lat": 13.020266, "lng": 77.61274, "location_name": "Shampura Main Road, Tiger Tippu Circle, Kadugondanahalli, Bengaluru, Karnataka. Pin-560045 (India)", "police_station": "K.G. Halli", "junction_name": "No Junction", "is_junction": false, "dominant_violation": "NO PARKING", "dominant_vehicle": "SCOOTER", "peak_hour": 11, "temporal_matrix": [[0.0, 0.0, 0.0, 0.0, 0.0, 0.0, 0.0, 0.0, 0.0, 0.0, 0.0, 0.0, 0.0, 0.0, 0.0, 0.0, 0.0, 0.0, 0.0, 0.0, 0.0, 0.0, 0.0, 0.0], [0.0, 0.0, 0.0, 0.0, 0.0, 0.0, 0.0, 0.0, 0.0, 0.0, 0.0, 2.0, 0.0, 0.0, 0.0, 0.0, 0.0, 0.0, 0.0, 0.0, 0.0, 0.0, 0.0, 0.0], [0.0, 0.0, 0.0, 0.0, 0.0, 0.0, 0.0, 0.0, 0.0, 0.0, 0.0, 0.0, 0.0, 0.0, 0.0, 0.0, 0.0, 0.0, 0.0, 0.0, 0.0, 0.0, 0.0, 0.0], [0.0, 0.0, 0.0, 0.0, 0.0, 0.0, 0.0, 0.0, 0.0, 0.0, 0.0, 0.0, 0.0, 0.0, 0.0, 0.0, 0.0, 0.0, 0.0, 0.0, 0.0, 0.0, 0.0, 0.0], [0.0, 0.0, 0.0, 0.0, 0.0, 0.0, 0.0, 0.0, 0.0, 0.0, 0.0, 0.0, 0.0, 0.0, 0.0, 0.0, 0.0, 0.0, 0.0, 0.0, 0.0, 0.0, 0.0, 0.0], [0.0, 0.0, 0.0, 0.0, 0.0, 0.0, 0.0, 0.0, 0.0, 0.0, 0.0, 0.0, 0.0, 0.0, 0.0, 0.0, 0.0, 0.0, 0.0, 0.0, 0.0, 0.0, 0.0, 0.0], [0.0, 0.0, 0.0, 0.0, 0.0, 0.0, 0.0, 0.0, 0.0, 0.0, 0.0, 0.0, 0.0, 0.0, 0.0, 0.0, 0.0, 0.0, 0.0, 0.0, 0.0, 0.0, 0.0, 0.0]], "violation_breakdown": {"NO PARKING": 2}, "vehicle_breakdown": {"SCOOTER": 2}, "monthly_trend": {"2024-01": 2}, "hourly_distribution": {"11": 2}, "neighbors": [{"hex_id": "8861892eb1fffff", "cis_score": 43.1, "violations": 39}, {"hex_id": "8861892eb5fffff", "cis_score": 38.2, "violations": 7}, {"hex_id": "8861892ccbfffff", "cis_score": 22.8, "violations": 10}], "ai_insight": "This hotspot in K.G. Halli averages 2 violations/day, peaking at 11:00. Primarily NO PARKING by SCOOTERs (2 incidents). causing an estimated 6% carriageway reduction. CIS score: 17.2/100 (low)."}