{"hex_id": "886189243dfffff", "cis_score": 41.9, "cis_category": "moderate", "total_violations": 19, "daily_average": 1.4, "carriageway_reduction": 4.0, "lat": 12.902711, "lng": 77.624843, "location_name": "Kodichikkanahalli Main Road, Bommanahalli, Bengaluru, Karnataka. Pin-560068 (India)", "police_station": "Madiwala", "junction_name": "No Junction", "is_junction": false, "dominant_violation": "WRONG PARKING", "dominant_vehicle": "PASSENGER AUTO", "peak_hour": 11, "temporal_matrix": [[0.0, 0.0, 0.0, 0.0, 0.0, 0.0, 0.0, 0.0, 0.0, 0.0, 0.0, 0.0, 0.0, 0.0, 0.0, 0.0, 0.0, 0.0, 0.0, 0.0, 0.0, 0.0, 0.0, 0.0], [0.0, 1.0, 0.0, 0.0, 0.0, 0.0, 0.0, 0.0, 0.0, 0.0, 2.0, 2.0, 1.0, 1.0, 0.0, 0.0, 0.0, 0.0, 0.0, 0.0, 0.0, 0.0, 0.0, 0.0], [0.0, 0.0, 0.0, 0.0, 0.0, 0.0, 0.0, 0.0, 0.0, 0.0, 1.0, 1.0, 1.0, 0.0, 0.0, 0.0, 0.0, 0.0, 0.0, 0.0, 0.0, 0.0, 0.0, 0.0], [0.0, 0.0, 0.0, 0.0, 0.0, 0.0, 0.0, 0.0, 0.0, 0.0, 2.0, 3.0, 0.0, 0.0, 1.0, 0.0, 0.0, 0.0, 0.0, 0.0, 0.0, 0.0, 0.0, 0.0], [0.0, 0.0, 0.0, 0.0, 2.0, 0.0, 0.0, 0.0, 0.0, 0.0, 0.0, 0.0, 0.0, 0.0, 0.0, 0.0, 0.0, 0.0, 0.0, 0.0, 0.0, 0.0, 0.0, 0.0], [0.0, 0.0, 0.0, 0.0, 0.0, 0.0, 0.0, 0.0, 0.0, 0.0, 0.0, 1.0, 0.0, 0.0, 0.0, 0.0, 0.0, 0.0, 0.0, 0.0, 0.0, 0.0, 0.0, 0.0], [0.0, 0.0, 0.0, 0.0, 0.0, 0.0, 0.0, 0.0, 0.0, 0.0, 0.0, 0.0, 0.0, 0.0, 0.0, 0.0, 0.0, 0.0, 0.0, 0.0, 0.0, 0.0, 0.0, 0.0]], "violation_breakdown": {"WRONG PARKING": 11, "NO PARKING": 8, "PARKING IN A MAIN ROAD": 2}, "vehicle_breakdown": {"PASSENGER AUTO": 6, "CAR": 6, "SCOOTER": 2, "MOTOR CYCLE": 2, "MOPED": 1, "LGV": 1, "VAN": 1}, "monthly_trend": {"2023-11": 6, "2023-12": 3, "2024-01": 7, "2024-03": 3}, "hourly_distribution": {"1": 1, "4": 2, "10": 5, "11": 7, "12": 2, "13": 1, "14": 1}, "neighbors": [{"hex_id": "8861892407fffff", "cis_score": 17.2, "violations": 1}, {"hex_id": "886189242bfffff", "cis_score": 47.7, "violations": 359}, {"hex_id": "8861892423fffff", "cis_score": 52.2, "violations": 154}, {"hex_id": "8861892431fffff", "cis_score": 13.3, "violations": 3}, {"hex_id": "8861892439fffff", "cis_score": 32.9, "violations": 3}], "ai_insight": "This hotspot in Madiwala averages 1 violations/day, peaking at 11:00. Primarily WRONG PARKING by PASSENGER AUTOs (6 incidents). on an arterial road, causing an estimated 4% carriageway reduction. CIS score: 41.9/100 (moderate)."}