{"hex_id": "8861892585fffff", "shap_values": {"hex_total_count": -1.2614, "avg_severity": -0.6251, "month_12_count": -0.3306, "month_11_count": -0.2814, "road_multiplier": -0.2793, "avg_lane_blockage": -0.2501, "month_1_count": -0.148, "hex_avg_severity": -0.0996, "is_junction": -0.054, "month_2_count": -0.0507, "month_3_count": -0.0497, "avg_vehicle_size": 0.0481, "hour_cos": -0.032, "day_of_week": -0.0243, "hour": 0.0109, "hour_sin": -0.0107, "dow_cos": -0.0085, "is_peak": 0.008, "dow_sin": 0.0077, "is_weekend": -0.0001}, "top_factors": [{"feature": "hex_total_count", "shap_value": -1.2614, "direction": "decreases", "description": "Historical violation volume at this location pushes prediction lower"}, {"feature": "avg_severity", "shap_value": -0.6251, "direction": "decreases", "description": "Average violation severity drives prediction lower"}, {"feature": "month_12_count", "shap_value": -0.3306, "direction": "decreases", "description": "Monthly seasonal pattern contributes to lower violations"}, {"feature": "month_11_count", "shap_value": -0.2814, "direction": "decreases", "description": "Monthly seasonal pattern contributes to lower violations"}, {"feature": "road_multiplier", "shap_value": -0.2793, "direction": "decreases", "description": "Road type/hierarchy makes congestion impact lower"}]}